{"心理":[{"title":"フロー状態とは？入り方や瞑想との関係","slug":"フロー状態"}],"ストレス":[{"title":"フロー状態とは？入り方や瞑想との関係","slug":"フロー状態"}],"フロー状態":[{"title":"フロー状態とは？入り方や瞑想との関係","slug":"フロー状態"}],"モチベーション":[{"title":"フロー状態とは？入り方や瞑想との関係","slug":"フロー状態"}],"瞑想":[{"title":"フロー状態とは？入り方や瞑想との関係","slug":"フロー状態"}],"TANITA":[{"title":"【体重計】TANITAのインナースキャンデュアル RD-800レビュー【感想】","slug":"TANITAインナースキャンデュアル"}],"体重計":[{"title":"【体重計】TANITAのインナースキャンデュアル RD-800レビュー【感想】","slug":"TANITAインナースキャンデュアル"}],"レビュー":[{"title":"【体重計】TANITAのインナースキャンデュアル RD-800レビュー【感想】","slug":"TANITAインナースキャンデュアル"}],"RD-800":[{"title":"【体重計】TANITAのインナースキャンデュアル RD-800レビュー【感想】","slug":"TANITAインナースキャンデュアル"}],"話し方":[{"title":"人に好かれるための科学的な話し方","slug":"好かれる話し方"}],"健康":[{"title":"科学的に食欲を減らす9つの方法","slug":"食欲を減らす方法"}],"ダイエット":[{"title":"科学的に食欲を減らす9つの方法","slug":"食欲を減らす方法"}],"食欲":[{"title":"科学的に食欲を減らす9つの方法","slug":"食欲を減らす方法"}]}